hurricore/__init__.py
hurricore/hooks/__init__.py
hurricore/hooks/checkpoint_hook.py
hurricore/hooks/hf_llm_peek_hook.py
hurricore/hooks/hook.py
hurricore/hooks/logger_hook.py
hurricore/hooks/lr_scheduler_hook.py
hurricore/hooks/sync_batch_norm_hook.py
hurricore/hooks/tensor_board_hook.py
hurricore/trainers/__init__.py
hurricore/trainers/hf_llm_trainer.py
hurricore/trainers/trainer.py
hurricore/utils/__init__.py
hurricore/utils/config_base.py
hurricore/utils/config_utils.py
hurricore/utils/context.py
hurricore/utils/dummy_object.py
hurricore/utils/easy_ops.py
hurricore/utils/logger.py
hurricore/utils/misc.py
hurricore/utils/collators/__init__.py
hurricore/utils/collators/hf_llm_it_collator.py
hurricore-0.1.1.dist-info/LICENSE
hurricore-0.1.1.dist-info/METADATA
hurricore-0.1.1.dist-info/WHEEL
hurricore-0.1.1.dist-info/top_level.txt
hurricore-0.1.1.dist-info/RECORD
